setup.py
adt/__init__.py
py_foldadt.egg-info/PKG-INFO
py_foldadt.egg-info/SOURCES.txt
py_foldadt.egg-info/dependency_links.txt
py_foldadt.egg-info/top_level.txt