Metadata-Version: 1.0
Name: py-foldadt
Version: 0.1.7
Summary: Zero dependency, mypy friendly algebraic data types
Home-page: https://github.com/beezee/py-foldadt
Author: beezee
Author-email: UNKNOWN
License: UNKNOWN
Project-URL: Source Code, https://github.com/beezee/py-foldadt
Keywords: algebraic data types,adt
Platform: UNKNOWN
